syncgrid/__init__.py
syncgrid/main.py
syncgrid-3.9.dist-info/METADATA
syncgrid-3.9.dist-info/WHEEL
syncgrid-3.9.dist-info/top_level.txt
syncgrid-3.9.dist-info/RECORD
