Metadata-Version: 2.1
Name: syncgrid
Version: 3.9
Summary: syncgrid, library for distributed systems
Author-email: syncgrid@gmail.com
